{
  "L1": {
    "title": "Unit 1: The Bet",
    "stages": {
      "1": [
        "BET", "FINANCIAL", "ALLOWANCE", "APPLICATION", "CHERISH", "FUND", "MILLION", "VOLUNTARY", "PUNISHMENT", "IMPRISON", "IMPRISONMENT", "LAWYER", "SUFFER", "BANKER", "EARTHLY", "DESPISE", "MATERIAL", "SPIRITUAL", "CONFINEMENT", "CONFINE", "FLEE", "WISDOM", "CAPTIVE",
        "MAKE A BET", "CAST ASIDE", "IN EXCHANGE FOR", "LOCK UP", "PASS THE TIME", "GIVE UP", "NO LONGER"
      ],
      "2": [
        "I BET YOU CANNOT DO IT",
        "THE COMPANY HAS FINANCIAL ISSUES",
        "HE RECEIVES A MONTHLY ALLOWANCE FROM HIS PARENTS",
        "HER APPLICATION FOR THE JOB WAS REJECTED",
        "ANNIE REALLY CHERISHES HER DOLL",
        "WE RAISED A FUND FOR CHARITY",
        "HE WON A MILLION DOLLARS",
        "IT WAS A VOLUNTARY CHOICE",
        "HE ESCAPED PUNISHMENT",
        "THE THIEF WAS IMPRISONED FOR TWO YEARS",
        "HE WAS SENTENCED TO LIFE IMPRISONMENT",
        "THE LAWYER DEFENDED HIM IN COURT",
        "SHE SUFFERED FROM A SEVERE HEADACHE",
        "THE BANKER IS VERY RICH",
        "HE DESPISED ALL EARTHLY POSSESSIONS",
        "DO NOT DESPISE THE POOR",
        "MATERIAL THINGS ARE NOT EVERYTHING",
        "HE SEEKS SPIRITUAL PEACE THROUGH MEDITATION",
        "HE WAS HELD IN SOLITARY CONFINEMENT",
        "PLEASE CONFINE YOUR DOG TO THE YARD",
        "THE PRISONER TRIED TO FLEE",
        "HE HAS GREAT WISDOM FOR HIS AGE",
        "THE CAPTIVE WAS FINALLY RELEASED",
        "THEY MADE A BET ON THE HORSE RACE",
        "YOU SHOULD CAST ASIDE YOUR FEARS",
        "HE GAVE HER A BOOK IN EXCHANGE FOR THE PEN",
        "THE PRISONER WAS LOCKED UP IN A SMALL CELL",
        "HE READ BOOKS TO PASS THE TIME",
        "NEVER GIVE UP ON YOUR DREAMS",
        "HE IS NO LONGER WORKING FOR THIS COMPANY"
      ]
    }
  },
  "L2": {

}
